flask_restalchemy/__init__.py
flask_restalchemy/api.py
flask_restalchemy/conftest.py
flask_restalchemy/serialization.py
flask_restalchemy/decorators/__init__.py
flask_restalchemy/decorators/request_hooks.py
flask_restalchemy/resources/__init__.py
flask_restalchemy/resources/querybuilder.py
flask_restalchemy/resources/resources.py
flask_restalchemy/tests/__init__.py
flask_restalchemy/tests/employer_serializer.py
flask_restalchemy/tests/sample_model.py
flask_restalchemy/tests/test_api.py
flask_restalchemy/tests/test_api_processors.py
flask_restalchemy/tests/test_api_relations.py
flask_restalchemy/tests/test_blueprint.py
flask_restalchemy/tests/test_child_resource.py
flask_restalchemy/tests/test_decorators.py
flask_restalchemy/tests/test_query_callback.py
flask_restalchemy/tests/test_querybuilder.py
flask_restalchemy/tests/test_simple_api.py
flask_restalchemy/tests/test_swagger_spec_gen.py
flask_restalchemy/tests/test_api/test_get.yml
flask_restalchemy/tests/test_api/test_get_collection.yml
flask_restalchemy/tests/test_api_relations/test_get_collection.yml
flask_restalchemy/tests/test_api_relations/test_get_item.yml
flask_restalchemy/tests/test_api_relations/test_property.yml
flask_restalchemy/tests/test_query_callback/test_get_collection_model.yml
flask_restalchemy/tests/test_query_callback/test_get_collection_property.yml
flask_restalchemy/tests/test_query_callback/test_get_collection_relation_protoss.yml
flask_restalchemy/tests/test_query_callback/test_get_collection_relation_terrans.yml
flask_restalchemy-0.14.1.dist-info/LICENSE
flask_restalchemy-0.14.1.dist-info/METADATA
flask_restalchemy-0.14.1.dist-info/WHEEL
flask_restalchemy-0.14.1.dist-info/top_level.txt
flask_restalchemy-0.14.1.dist-info/RECORD
